yiff/__init__.py
yiff/yiff.py
yiffpy-0.2.1.dist-info/LICENSE
yiffpy-0.2.1.dist-info/METADATA
yiffpy-0.2.1.dist-info/WHEEL
yiffpy-0.2.1.dist-info/top_level.txt
yiffpy-0.2.1.dist-info/RECORD
