Metadata-Version: 2.1
Name: yiffpy
Version: 0.2.1
Summary: Test package for e6
Home-page: https://github.com/Blobadoodle/e621-wrapper
Author: Blobadoodle
Author-email: blobadoodle@gmail.com
License: UNKNOWN
Project-URL: Bug Tracker, https://github.com/Blobadoodle/e621-wrapper/issues
Platform: UNKNOWN
Classifier: Programming Language :: Python :: 3
Classifier: License :: OSI Approved :: MIT License
Classifier: Operating System :: OS Independent
Requires-Python: >=3.6
License-File: LICENSE
Requires-Dist: requests
Requires-Dist: ratelimit
